[
    {
      "team": "Web Dev",
      "members": [
        {
          "name": "Hari Om Meena",
          "image": "/assets/hari.jpeg",
          "linkedin": "https://www.linkedin.com/in/hariom-meena"
        },
        {
          "name": "Anjali Sharma",
          "image": "/assets/anjali.jpeg",
          "linkedin": "https://www.linkedin.com/in/anjali-sharma"
        }
      ]
    },
    {
      "team": "App Dev",
      "members": [
        {
          "name": "Rohan Gupta",
          "image": "/assets/rohan.jpeg",
          "linkedin": "https://www.linkedin.com/in/rohan-gupta"
        },
        {
          "name": "Simran Kaur",
          "image": "/assets/simran.jpeg",
          "linkedin": "https://www.linkedin.com/in/simran-kaur"
        }
      ]
    },
    {
      "team": "PR/Social Media",
      "members": [
        {
          "name": "Priya Verma",
          "image": "/assets/priya.jpeg",
          "linkedin": "https://www.linkedin.com/in/priya-verma"
        },
        {
          "name": "Manish Patel",
          "image": "/assets/manish.jpeg",
          "linkedin": "https://www.linkedin.com/in/manish-patel"
        }
      ]
    },
    {
      "team": "Cloud/ML",
      "members": [
        {
          "name": "Aditi Rao",
          "image": "/assets/aditi.jpeg",
          "linkedin": "https://www.linkedin.com/in/aditi-rao"
        },
        {
          "name": "Kartik Singh",
          "image": "/assets/kartik.jpeg",
          "linkedin": "https://www.linkedin.com/in/kartik-singh"
        }
      ]
    }
  ]
  